openfga_dsl_parser_python-0.1.0.dist-info/METADATA
openfga_dsl_parser_python-0.1.0.dist-info/WHEEL
openfga_dsl_parser_python-0.1.0.dist-info/license_files/LICENSE
openfga_dsl_parser/__init__.py
openfga_dsl_parser/openfga_dsl_parser.cpython-37m-x86_64-linux-gnu.so
openfga_dsl_parser_python-0.1.0.dist-info/RECORD
